mult/mult.v
module mult(
	clk,
	reset,
	in,
	w,
	out
);

//Data is stored as an 8.8 fixed point number
input clk;
input reset;
input [15:0] in;
input [15:0] w;
output [15:0] out;

//Define constants
parameter vecLen=16;

//Define variables
integer i;

reg [31:0] layer1 [15:0];
reg [31:0] layer2 [7:0];
reg [31:0] layer3 [3:0];
reg [31:0] layer4 [1:0];
reg [31:0] layer5;
/***********************************************************************
Because there are 5 layers, this design takes 5 clock cylces to complete
***********************************************************************/


//Tie the output pin to the last register's (layer5) output 
assign out = layer5[23:8];

//Define the pipelined multiplier data path
always @(posedge clk) 
begin
	//If reset is held high, clear the pipelined registers
	if (reset==1) begin
		for (i=0; i<vecLen; i=i+1)begin	
			layer1[i]<=0;
		end	
		for (i=0; i<vecLen/2; i=i+1)begin	
			layer2[i]<=0;
		end
		for (i=0; i<vecLen/4; i=i+1)begin	
			layer3[i]<=0;
		end			
		for (i=0; i<vecLen/8; i=i+1)begin	
			layer4[i]<=0;
		end	
		layer5 <= 0;
		
	end
	//If reset is low, perform normal multiplier operations
	else begin
	/*******************************SIGNED***************************/
		//***************Layer1****************************
		//AND each bit of the weight function with the input	
		layer1[0][16:0]<= {1'b1, ~(w[0] & in[15]), {15{w[0]}} & in[14:0]};
		layer1[1][16:1]<= {~(w[1] & in[15]), {15{w[1]}} & in[14:0]};
		layer1[2][17:2]<= {~(w[2] & in[15]), {15{w[2]}} & in[14:0]};
		layer1[3][18:3]<= {~(w[3] & in[15]), {15{w[3]}} & in[14:0]};
		layer1[4][19:4]<= {~(w[4] & in[15]), {15{w[4]}} & in[14:0]};
		layer1[5][20:5]<= {~(w[5] & in[15]), {15{w[5]}} & in[14:0]};
		layer1[6][21:6]<= {~(w[6] & in[15]), {15{w[6]}} & in[14:0]};
		layer1[7][22:7]<= {~(w[7] & in[15]), {15{w[7]}} & in[14:0]};
		layer1[8][23:8]<= {~(w[8] & in[15]), {15{w[8]}} & in[14:0]};
		layer1[9][24:9]<= {~(w[9] & in[15]), {15{w[9]}} & in[14:0]};
		layer1[10][25:10]<= {~(w[10] & in[15]), {15{w[10]}} & in[14:0]};
		layer1[11][26:11]<= {~(w[11] & in[15]), {15{w[11]}} & in[14:0]};
		layer1[12][27:12]<= {~(w[12] & in[15]), {15{w[12]}} & in[14:0]};
		layer1[13][28:13]<= {~(w[13] & in[15]), {15{w[13]}} & in[14:0]};
		layer1[14][29:14]<= {~(w[14] & in[15]), {15{w[14]}} & in[14:0]};
		layer1[15][31:15]<= {1'b1, (w[15] & in[15]), ~({15{w[15]}} & in[14:0])};

	
		//***************Layer2****************************
		//Start adding the results of the and

		layer2[0] <= layer1[0] + layer1[1];
		layer2[1] <= layer1[2] + layer1[3];
		layer2[2] <= layer1[4] + layer1[5];
		layer2[3] <= layer1[6] + layer1[7];
		layer2[4] <= layer1[8] + layer1[9];
		layer2[5] <= layer1[10] + layer1[11];
		layer2[6] <= layer1[12] + layer1[13];
		layer2[7] <= layer1[14] + layer1[15];
		
		
		//***************Layer3****************************
		//Continue adding outputs
		layer3[0] <= layer2[0] + layer2[1];
		layer3[1] <= layer2[2] + layer2[3];
		layer3[2] <= layer2[4] + layer2[5];
		layer3[3] <= layer2[6] + layer2[7];
		
		//***************Layer4****************************
		//Continue adding outputs
		layer4[0] <= layer3[0] + layer3[1];
		layer4[1] <= layer3[2] + layer3[3];
		
		//***************Layer5****************************
		//Calculate the final result of the multiplier
		layer5 <= layer4[0] + layer4[1];
	/****************************END SIGNED**************************/





	/******************************UNSIGNED***************************
		//***************Layer1****************************
		//AND each bit of the weight function with the input	
		layer1[0][15:0]<= {16{w[0]}} & in;
		layer1[1][16:1]<= {16{w[1]}} & in;
		layer1[2][17:2]<= {16{w[2]}} & in;
		layer1[3][18:3]<= {16{w[3]}} & in;
		layer1[4][19:4]<= {16{w[4]}} & in;
		layer1[5][20:5]<= {16{w[5]}} & in;
		layer1[6][21:6]<= {16{w[6]}} & in;
		layer1[7][22:7]<= {16{w[7]}} & in;
		layer1[8][23:8]<= {16{w[8]}} & in;
		layer1[9][24:9]<= {16{w[9]}} & in;
		layer1[10][25:10]<= {16{w[10]}} & in;
		layer1[11][26:11]<= {16{w[11]}} & in;
		layer1[12][27:12]<= {16{w[12]}} & in;
		layer1[13][28:13]<= {16{w[13]}} & in;
		layer1[14][29:14]<= {16{w[14]}} & in;
		layer1[15][30:15]<= {16{w[15]}} & in;


		//***************Layer2****************************
		//Start adding the results of the and

		layer2[0] <= layer1[0] + layer1[1];
		layer2[1] <= layer1[2] + layer1[3];
		layer2[2] <= layer1[4] + layer1[5];
		layer2[3] <= layer1[6] + layer1[7];
		layer2[4] <= layer1[8] + layer1[9];
		layer2[5] <= layer1[10] + layer1[11];
		layer2[6] <= layer1[12] + layer1[13];
		layer2[7] <= layer1[14] + layer1[15];
		
		
		//***************Layer3****************************
		//Continue adding outputs
		layer3[0] <= layer2[0] + layer2[1];
		layer3[1] <= layer2[2] + layer2[3];
		layer3[2] <= layer2[4] + layer2[5];
		layer3[3] <= layer2[6] + layer2[7];
		
		//***************Layer4****************************
		//Continue adding outputs
		layer4[0] <= layer3[0] + layer3[1];
		layer4[1] <= layer3[2] + layer3[3];
		
		//***************Layer5****************************
		//Calculate the final result of the multiplier
		layer5 <= layer4[0] + layer4[1];
	**************************End Unsigned*****************************/
	end

end


endmodule

mult/mult_tb.v
`timescale 1ns / 1ps

module mult_tb();

    reg  clk;
    reg  reset;
    reg [15:0] in;
    reg [15:0] w;
    wire [15:0] out;

  

    mult DUT(
        .clk(clk),
        .reset(reset),
	.in(in),
	.w(w),
	.out(out)
        );

    initial
    begin
        $dumpfile("mult.vcd");
        $dumpvars(0, mult_tb);

        reset = 1;
        clk = 0;
	
	in= 16'hffff;
	w = 16'h0200;

        // 1
        #16
        reset = 0;

	#20
	in= 16'h0100;
	w = 16'h0100;

	#20
	in= 16'h1100;
	w = 16'h0100;	

	#20
	in= 16'h0100;
	w = 16'h01ff;

        #300
	//Let it run
	
        $finish;
    end

    always 
        #10 clk = !clk;

endmodule

mult/mult.vcd
$date
	Mon Dec  4 19:42:24 2017
$end

$version
	Synopsys VCS version J-2014.12-SP1-1_Full64
$end

$timescale
	1ps
$end

$comment Csum: 1 ed8e1e6cd3a3739a $end


$scope module mult_tb $end
$var reg 1 ! clk $end
$var reg 1 " reset $end
$var reg 16 # in [15:0] $end
$var reg 16 $ w [15:0] $end
$var wire 16 % out [15:0] $end

$scope module DUT $end
$var wire 1 ! clk $end
$var wire 1 " reset $end
$var wire 16 # in [15:0] $end
$var wire 1 & w [15] $end
$var wire 1 ' w [14] $end
$var wire 1 ( w [13] $end
$var wire 1 ) w [12] $end
$var wire 1 * w [11] $end
$var wire 1 + w [10] $end
$var wire 1 , w [9] $end
$var wire 1 - w [8] $end
$var wire 1 . w [7] $end
$var wire 1 / w [6] $end
$var wire 1 0 w [5] $end
$var wire 1 1 w [4] $end
$var wire 1 2 w [3] $end
$var wire 1 3 w [2] $end
$var wire 1 4 w [1] $end
$var wire 1 5 w [0] $end
$var wire 16 % out [15:0] $end
$var integer 32 6 i $end
$var reg 32 7 layer5 [31:0] $end
$upscope $end

$upscope $end

$enddefinitions $end

#0
$dumpvars
0!
1"
05
0+
0*
0)
0(
0'
0&
04
03
02
01
00
0/
0.
0-
1,
bxxxxxxxxxxxxxxxxxxxxxxxxxxxxxxxx 6
b1111111111111111 #
bxxxxxxxxxxxxxxxxxxxxxxxxxxxxxxxx 7
bxxxxxxxxxxxxxxxx %
b0000001000000000 $
$end
#10000
1!
b00000000000000000000000000000010 6
b00000000000000000000000000000000 7
b0000000000000000 %
#16000
0"
#20000
0!
#30000
1!
#36000
b0000000100000000 #
b0000000100000000 $
0,
1-
#40000
0!
#50000
1!
#56000
b0001000100000000 #
#60000
0!
#70000
1!
#76000
b0000000100000000 #
b0000000111111111 $
1.
1/
10
11
12
13
14
15
#80000
0!
#90000
1!
#100000
0!
#110000
1!
b11111111111111111111111000000000 7
b1111111111111110 %
#120000
0!
#130000
1!
b00000000000000010000000000000000 7
b0000000100000000 %
#140000
0!
#150000
1!
b00000000000100010000000000000000 7
b0001000100000000 %
#160000
0!
#170000
1!
b00000000000000011111111100000000 7
b0000000111111111 %
