mac/mult.v
module mult(
	clk,
	reset,
	in,
	w,
	out
);

//Data is stored as an 8.8 fixed point number
input clk;
input reset;
input signed [15:0] in;
input signed [15:0] w;
output signed [15:0] out;

//Define constants
parameter vecLen=16;

//Define variables
integer i;

reg signed [31:0] layer1 [15:0];
reg signed [31:0] layer2 [7:0];
reg signed [31:0] layer3 [3:0];
reg signed [31:0] layer4 [1:0];
reg signed [31:0] layer5;
/***********************************************************************
Because there are 5 layers, this design takes 5 clock cylces to complete
***********************************************************************/


//Tie the output pin to the last register's (layer5) output 
assign out = layer5[23:8];

//Define the pipelined multiplier data path
always @(posedge clk) 
begin
	//If reset is held high, clear the pipelined registers
	if (reset==1) begin
		for (i=0; i<vecLen; i=i+1)begin	
			layer1[i]<=0;
		end	
		for (i=0; i<vecLen/2; i=i+1)begin	
			layer2[i]<=0;
		end
		for (i=0; i<vecLen/4; i=i+1)begin	
			layer3[i]<=0;
		end			
		for (i=0; i<vecLen/8; i=i+1)begin	
			layer4[i]<=0;
		end	
		layer5 <= 0;
		
	end
	//If reset is low, perform normal multiplier operations
	else begin
	/*******************************SIGNED***************************/
		//***************Layer1****************************
		//AND each bit of the weight function with the input	
		layer1[0][16:0]<= {1'b1, ~(w[0] & in[15]), {15{w[0]}} & in[14:0]};
		layer1[1][16:1]<= {~(w[1] & in[15]), {15{w[1]}} & in[14:0]};
		layer1[2][17:2]<= {~(w[2] & in[15]), {15{w[2]}} & in[14:0]};
		layer1[3][18:3]<= {~(w[3] & in[15]), {15{w[3]}} & in[14:0]};
		layer1[4][19:4]<= {~(w[4] & in[15]), {15{w[4]}} & in[14:0]};
		layer1[5][20:5]<= {~(w[5] & in[15]), {15{w[5]}} & in[14:0]};
		layer1[6][21:6]<= {~(w[6] & in[15]), {15{w[6]}} & in[14:0]};
		layer1[7][22:7]<= {~(w[7] & in[15]), {15{w[7]}} & in[14:0]};
		layer1[8][23:8]<= {~(w[8] & in[15]), {15{w[8]}} & in[14:0]};
		layer1[9][24:9]<= {~(w[9] & in[15]), {15{w[9]}} & in[14:0]};
		layer1[10][25:10]<= {~(w[10] & in[15]), {15{w[10]}} & in[14:0]};
		layer1[11][26:11]<= {~(w[11] & in[15]), {15{w[11]}} & in[14:0]};
		layer1[12][27:12]<= {~(w[12] & in[15]), {15{w[12]}} & in[14:0]};
		layer1[13][28:13]<= {~(w[13] & in[15]), {15{w[13]}} & in[14:0]};
		layer1[14][29:14]<= {~(w[14] & in[15]), {15{w[14]}} & in[14:0]};
		layer1[15][31:15]<= {1'b1, (w[15] & in[15]), ~({15{w[15]}} & in[14:0])};

	
		//***************Layer2****************************
		//Start adding the results of the and

		layer2[0] <= layer1[0] + layer1[1];
		layer2[1] <= layer1[2] + layer1[3];
		layer2[2] <= layer1[4] + layer1[5];
		layer2[3] <= layer1[6] + layer1[7];
		layer2[4] <= layer1[8] + layer1[9];
		layer2[5] <= layer1[10] + layer1[11];
		layer2[6] <= layer1[12] + layer1[13];
		layer2[7] <= layer1[14] + layer1[15];
		
		
		//***************Layer3****************************
		//Continue adding outputs
		layer3[0] <= layer2[0] + layer2[1];
		layer3[1] <= layer2[2] + layer2[3];
		layer3[2] <= layer2[4] + layer2[5];
		layer3[3] <= layer2[6] + layer2[7];
		
		//***************Layer4****************************
		//Continue adding outputs
		layer4[0] <= layer3[0] + layer3[1];
		layer4[1] <= layer3[2] + layer3[3];
		
		//***************Layer5****************************
		//Calculate the final result of the multiplier
		layer5 <= layer4[0] + layer4[1];
	/****************************END SIGNED**************************/





	/******************************UNSIGNED***************************
		//***************Layer1****************************
		//AND each bit of the weight function with the input	
		layer1[0][15:0]<= {16{w[0]}} & in;
		layer1[1][16:1]<= {16{w[1]}} & in;
		layer1[2][17:2]<= {16{w[2]}} & in;
		layer1[3][18:3]<= {16{w[3]}} & in;
		layer1[4][19:4]<= {16{w[4]}} & in;
		layer1[5][20:5]<= {16{w[5]}} & in;
		layer1[6][21:6]<= {16{w[6]}} & in;
		layer1[7][22:7]<= {16{w[7]}} & in;
		layer1[8][23:8]<= {16{w[8]}} & in;
		layer1[9][24:9]<= {16{w[9]}} & in;
		layer1[10][25:10]<= {16{w[10]}} & in;
		layer1[11][26:11]<= {16{w[11]}} & in;
		layer1[12][27:12]<= {16{w[12]}} & in;
		layer1[13][28:13]<= {16{w[13]}} & in;
		layer1[14][29:14]<= {16{w[14]}} & in;
		layer1[15][30:15]<= {16{w[15]}} & in;


		//***************Layer2****************************
		//Start adding the results of the and

		layer2[0] <= layer1[0] + layer1[1];
		layer2[1] <= layer1[2] + layer1[3];
		layer2[2] <= layer1[4] + layer1[5];
		layer2[3] <= layer1[6] + layer1[7];
		layer2[4] <= layer1[8] + layer1[9];
		layer2[5] <= layer1[10] + layer1[11];
		layer2[6] <= layer1[12] + layer1[13];
		layer2[7] <= layer1[14] + layer1[15];
		
		
		//***************Layer3****************************
		//Continue adding outputs
		layer3[0] <= layer2[0] + layer2[1];
		layer3[1] <= layer2[2] + layer2[3];
		layer3[2] <= layer2[4] + layer2[5];
		layer3[3] <= layer2[6] + layer2[7];
		
		//***************Layer4****************************
		//Continue adding outputs
		layer4[0] <= layer3[0] + layer3[1];
		layer4[1] <= layer3[2] + layer3[3];
		
		//***************Layer5****************************
		//Calculate the final result of the multiplier
		layer5 <= layer4[0] + layer4[1];
	**************************End Unsigned*****************************/
	end

end


endmodule

mac/mac.v
module mac(
	clk,
	reset,
	start,	
	done,	
	mac_in,
	weight,
	mac_out	
);

input clk;
input reset;
input start;	//Set start high whenever you enter a new data set
output done;	//Done is output when the MAC is done and restarting calculations with a new set
input [15:0] mac_in;
input [15:0] weight;
output [15:0] mac_out;

//Define variables
reg [15:0] psum;
wire [15:0] mult_out;

//Stages 1-5 correspond to the multiplier module
//Stage 6 corresponds to the accumulate stage
reg stage1, stage2, stage3, stage4, stage5, stage6;

mult mult1(clk, reset, mac_in, weight, mult_out);

assign mac_out = psum;
assign done = stage6;

always @(posedge clk) 
begin
	//Reset if reset is high 
	if(reset==1) begin
		psum<=0;
		stage1<=0;
		stage2<=0;
		stage3<=0;
		stage4<=0;
		stage5<=0;
	end
	
	//If stage6==1, the next input to psum must be from a new data set
	else if(stage6==1) begin
		#3 psum<=mult_out;

		//Keep track of the delay of data through the pipeline
		stage1<=start;
		stage2<=stage1;
		stage3<=stage2;
		stage4<=stage3;
		stage5<=stage4;
		stage6<=stage5;

	end
	else begin
		//Update the psum
		#3 psum<= psum + mult_out;

		//Keep track of the delay of data through the pipeline
		stage1<=start;
		stage2<=stage1;
		stage3<=stage2;
		stage4<=stage3;
		stage5<=stage4;
		stage6<=stage5;

	end





end

endmodule

mac/mac_tb.v
`timescale 1ns / 1ps

module mac_tb();

    reg  clk;
    reg  reset;
    reg start;
    //reg  done;
    reg [15:0] mac_in;
    reg [15:0] weight;
    wire [15:0] mac_out;

  

    mac DUT(
        .clk(clk),
        .reset(reset),
	.start(start),
	.done(done),
	.mac_in(mac_in),
	.weight(weight),
	.mac_out(mac_out)
        );

    initial
    begin
        $dumpfile("mac.vcd");
        $dumpvars(0, mac_tb);

        reset = 1;
        clk = 0;
	start=0;
	
	mac_in= 16'h0100;
	weight= 16'h0100;

        // 1
        #16
        reset = 0;
	start=1;
	
	#20
	start=0;
	mac_in= 16'h0100;
	weight= 16'h0100;

	#200
	mac_in= 16'h0100;
	weight= 16'h0100;


	#20
	start=1;
	mac_in= 16'h0100;
	weight= 16'h0100;


	#20
	start=0;
	mac_in= 16'h0100;
	weight= 16'h0100;

	#20
	mac_in= 16'h0100;
	weight= 16'h0100;

        #300
	//Let it run
	
        $finish;
    end

    always 
        #10 clk = !clk;

endmodule

mac/mac.vcd
$date
	Sat Dec  2 16:14:10 2017
$end

$version
	Synopsys VCS version J-2014.12-SP1-1_Full64
$end

$timescale
	1ps
$end

$comment Csum: 1 8af1ea3ba7cb4214 $end


$scope module mac_tb $end
$var reg 1 ! clk $end
$var reg 1 " reset $end
$var reg 1 # start $end
$var reg 16 $ mac_in [15:0] $end
$var reg 16 % weight [15:0] $end
$var wire 16 & mac_out [15:0] $end
$var wire 1 ' done $end

$scope module DUT $end
$var wire 1 ! clk $end
$var wire 1 " reset $end
$var wire 1 # start $end
$var wire 1 ' done $end
$var wire 16 $ mac_in [15:0] $end
$var wire 1 ( weight [15] $end
$var wire 1 ) weight [14] $end
$var wire 1 * weight [13] $end
$var wire 1 + weight [12] $end
$var wire 1 , weight [11] $end
$var wire 1 - weight [10] $end
$var wire 1 . weight [9] $end
$var wire 1 / weight [8] $end
$var wire 1 0 weight [7] $end
$var wire 1 1 weight [6] $end
$var wire 1 2 weight [5] $end
$var wire 1 3 weight [4] $end
$var wire 1 4 weight [3] $end
$var wire 1 5 weight [2] $end
$var wire 1 6 weight [1] $end
$var wire 1 7 weight [0] $end
$var wire 16 & mac_out [15:0] $end
$var reg 16 8 psum [15:0] $end
$var wire 16 9 mult_out [15:0] $end
$var reg 1 : stage1 $end
$var reg 1 ; stage2 $end
$var reg 1 < stage3 $end
$var reg 1 = stage4 $end
$var reg 1 > stage5 $end
$var reg 1 ? stage6 $end

$scope module mult1 $end
$var wire 1 ! clk $end
$var wire 1 " reset $end
$var wire 16 $ in [15:0] $end
$var wire 1 ( w [15] $end
$var wire 1 ) w [14] $end
$var wire 1 * w [13] $end
$var wire 1 + w [12] $end
$var wire 1 , w [11] $end
$var wire 1 - w [10] $end
$var wire 1 . w [9] $end
$var wire 1 / w [8] $end
$var wire 1 0 w [7] $end
$var wire 1 1 w [6] $end
$var wire 1 2 w [5] $end
$var wire 1 3 w [4] $end
$var wire 1 4 w [3] $end
$var wire 1 5 w [2] $end
$var wire 1 6 w [1] $end
$var wire 1 7 w [0] $end
$var wire 16 9 out [15:0] $end
$var integer 32 @ i $end
$var reg 32 A layer5 [31:0] $end
$upscope $end

$upscope $end

$upscope $end

$enddefinitions $end

#0
$dumpvars
0!
x'
1"
x:
x;
x<
x=
x>
x?
0#
07
0-
0,
0+
0*
0)
0(
06
05
04
03
02
01
00
1/
0.
bxxxxxxxxxxxxxxxxxxxxxxxxxxxxxxxx @
bxxxxxxxxxxxxxxxxxxxxxxxxxxxxxxxx A
b0000000100000000 $
bxxxxxxxxxxxxxxxx &
bxxxxxxxxxxxxxxxx 9
bxxxxxxxxxxxxxxxx 8
b0000000100000000 %
$end
#10000
1!
b00000000000000000000000000000010 @
b0000000000000000 8
b0000000000000000 &
0:
0;
0<
0=
0>
b00000000000000000000000000000000 A
b0000000000000000 9
#16000
0"
1#
#20000
0!
#30000
1!
#33000
1:
0?
0'
#36000
0#
#40000
0!
#50000
1!
#53000
0:
1;
#60000
0!
#70000
1!
#73000
0;
1<
#80000
0!
#90000
1!
#93000
0<
1=
#100000
0!
#110000
1!
b00000000000000010000000000000000 A
b0000000100000000 9
#113000
b0000000100000000 8
b0000000100000000 &
0=
1>
#120000
0!
#130000
1!
#133000
b0000001000000000 8
b0000001000000000 &
0>
1?
1'
#140000
0!
#150000
1!
#153000
b0000000100000000 8
b0000000100000000 &
0?
0'
#160000
0!
#170000
1!
#173000
b0000001000000000 8
b0000001000000000 &
#180000
0!
#190000
1!
#193000
b0000001100000000 8
b0000001100000000 &
#200000
0!
#210000
1!
#213000
b0000010000000000 8
b0000010000000000 &
#220000
0!
#230000
1!
#233000
b0000010100000000 8
b0000010100000000 &
#240000
0!
#250000
1!
#253000
b0000011000000000 8
b0000011000000000 &
#256000
1#
#260000
0!
#270000
1!
#273000
b0000011100000000 8
b0000011100000000 &
1:
#276000
0#
#280000
0!
#290000
1!
#293000
b0000100000000000 8
b0000100000000000 &
0:
1;
#300000
0!
#310000
1!
#313000
b0000100100000000 8
b0000100100000000 &
0;
1<
#320000
0!
#330000
1!
#333000
b0000101000000000 8
b0000101000000000 &
0<
1=
#340000
0!
#350000
1!
#353000
b0000101100000000 8
b0000101100000000 &
0=
1>
#360000
0!
#370000
1!
#373000
b0000110000000000 8
b0000110000000000 &
0>
1?
1'
#380000
0!
#390000
1!
#393000
b0000000100000000 8
b0000000100000000 &
0?
0'
#400000
0!
#410000
1!
#413000
b0000001000000000 8
b0000001000000000 &
#420000
0!
#430000
1!
#433000
b0000001100000000 8
b0000001100000000 &
#440000
0!
#450000
1!
#453000
b0000010000000000 8
b0000010000000000 &
#460000
0!
#470000
1!
#473000
b0000010100000000 8
b0000010100000000 &
#480000
0!
#490000
1!
#493000
b0000011000000000 8
b0000011000000000 &
#500000
0!
#510000
1!
#513000
b0000011100000000 8
b0000011100000000 &
#520000
0!
#530000
1!
#533000
b0000100000000000 8
b0000100000000000 &
#540000
0!
#550000
1!
#553000
b0000100100000000 8
b0000100100000000 &
#560000
0!
#570000
1!
#573000
b0000101000000000 8
b0000101000000000 &
#580000
0!
#590000
1!
#593000
b0000101100000000 8
b0000101100000000 &
