sigmoid/sigmoid.v
module sigmoid(
	clk,
	reset,
	done,
	sig_ready,
	sig_in,
	sig_out
);

//Data is stored as an 8.8 fixed point number
input clk;
input reset;
input done;
input signed [15:0] sig_in;
output [15:0] sig_out;
output sig_ready;

reg signed [15:0] x [120:0];	//Create the memory for the input ranges to the sigmoid
reg signed [15:0] LUT [120:0];	//Create the memory for the outputs to the sigmoid
reg signed [15:0] y;		//Store the output of the LUT
reg sig_rdy;

integer i;


//Tie the output of the LUT register to the output of the sigmoid module
assign sig_out = y;

//Tie the sigmoid ready register to its output
assign sig_ready = sig_rdy;
	
//Define the sigmoid lookup table
always @(posedge clk) 
begin
	//If reset is held high reset
	if (reset==1) begin
		y<=0;
		sig_rdy<=0;
	end
	//If the MAC output is ready, compare it to the lookup table
	else if (done==1) begin
		//Implement the lookup table
		//If the input is less than 6
		if (sig_in >= $signed(16'b1111101000000000) && sig_in <= $signed(16'b0000011000000000)) begin
			for (i=0; i<120; i=i+1) begin
				//If the sigmoid input is between two registers, it must be
				//in that bin
				if ((sig_in >= x[i]) && (sig_in < x[i+1])) begin
				//if (sig_in <= x[i] && sig_in > x[i+1]) begin
					//Assign the lower y-value bin to the output register
					y<=LUT[i];
				end
			end
		end
		else if (sig_in < $signed(16'b1111101000000000)) begin
			y<=16'h0000;
		end

		//If the input is more than 6
		else if (sig_in > $signed(16'b0000011000000000)) begin
			y<=16'h0100;
		end
		
	/*
		if (sig_in < $signed(16'b1111101000000000)) begin
			y<=16'h0000;
		end
		//If the input is more than 6
		else if (sig_in > $signed(16'b0000011000000000)) begin
			y<=16'h0100;
		end
		//Otherwise go to the LUT
		else begin
			//Replicate bin comparitor logic
			for (i=0; i<120; i=i+1) begin
				//If the sigmoid input is between two registers, it must be
				//in that bin
				if ((sig_in >= x[i]) && (sig_in < x[i+1])) begin
				//if (sig_in <= x[i] && sig_in > x[i+1]) begin
					//Assign the lower y-value bin to the output register
					y<=LUT[i];
				end
			end
		end
	*/

		
		//The sigmoid function is now ready
		#5 sig_rdy <= 1;


	end
end


endmodule

sigmoid/sigmoid_tb.v
`timescale 1ns / 1ps

module sigmoid_tb();

    reg  clk;
    reg  reset;
    reg  done;

    reg  [15:0] sig_in;
    //reg [15:0] x [120:0];	//Create the memory for the input ranges to the sigmoid
  //  reg [15:0] LUT [120:0];	//Create the memory for the outputs to the sigmoid
   // reg [15:0] y;		//Store the output of the LUT

    wire [15:0] sig_out;
    wire sig_ready;

    integer j;

    sigmoid DUT(
        .clk(clk),
        .reset(reset),
	.done(done),
	.sig_ready(sig_ready),
	.sig_in(sig_in),
	.sig_out(sig_out)
        );

    initial
    begin
        $dumpfile("sigmoid.vcd");
        $dumpvars(0, sigmoid_tb);

        reset = 1;
        clk = 0;
	done=1;
	
	$readmemb("x_fix.txt", DUT.x);
	$readmemb("y_fix.txt", DUT.LUT);

        // 1
        #16
        reset = 0;

	//For troubleshooting
	//Print the contents of the x and LUT rams to the terminal
	/*for(j=0; j<121; j=j+1) begin
		$display("index: %d		x: %h		LUT: %h", j, x[j], LUT[j]);
		
	end
	*/

	#20 
	//0.512
	sig_in=16'h0083;

	#20
	done = 0; 

	#20
	reset = 1; 

	#20
	reset = 0; 

	#20 
	done = 1; 

	#20
	//3.43
	sig_in=16'h036E;

	#20
	//6.5
	sig_in=16'h0680;
	
	#20
	//-6.xxxxxx
	sig_in=16'hfd00;

	#20
	//-128
	sig_in=16'h8000;
	

        #100
	//Let it run
	
        $finish;
    end

    always 
        #10 clk = !clk;

endmodule

sigmoid/sigmoid.vcd
$date
	Sun Dec  3 12:44:23 2017
$end

$version
	Synopsys VCS version J-2014.12-SP1-1_Full64
$end

$timescale
	1ps
$end

$comment Csum: 1 99c8242f11478842 $end


$scope module sigmoid_tb $end
$var reg 1 ! clk $end
$var reg 1 " reset $end
$var reg 1 # done $end
$var reg 16 $ sig_in [15:0] $end
$var wire 16 % sig_out [15:0] $end
$var wire 1 & sig_ready $end
$var integer 32 ' j $end

$scope module DUT $end
$var wire 1 ! clk $end
$var wire 1 " reset $end
$var wire 1 # done $end
$var wire 16 ( sig_in [15:0] $end
$var wire 16 % sig_out [15:0] $end
$var wire 1 & sig_ready $end
$var reg 16 ) y [15:0] $end
$var reg 1 * sig_rdy $end
$var integer 32 + i $end
$upscope $end

$upscope $end

$enddefinitions $end

#0
$dumpvars
0!
1#
1"
x*
x&
bxxxxxxxxxxxxxxxx (
bxxxxxxxxxxxxxxxxxxxxxxxxxxxxxxxx +
bxxxxxxxxxxxxxxxxxxxxxxxxxxxxxxxx '
bxxxxxxxxxxxxxxxx $
bxxxxxxxxxxxxxxxx %
bxxxxxxxxxxxxxxxx )
$end
#10000
1!
b0000000000000000 )
b0000000000000000 %
0*
0&
#16000
0"
#20000
0!
#30000
1!
#35000
1*
1&
#36000
b0000000010000011 $
b0000000010000011 (
#40000
0!
#50000
1!
b00000000000000000000000001111000 +
b0000000010011111 )
b0000000010011111 %
#56000
0#
#60000
0!
#70000
1!
#76000
1"
#80000
0!
#90000
1!
b0000000000000000 )
b0000000000000000 %
0*
0&
#96000
0"
#100000
0!
#110000
1!
#116000
1#
#120000
0!
#130000
1!
b0000000010011111 )
b0000000010011111 %
#135000
1*
1&
#136000
b0000001101101110 $
b0000001101101110 (
#140000
0!
#150000
1!
b0000000011111000 )
b0000000011111000 %
#156000
b0000011010000000 $
b0000011010000000 (
#160000
0!
#170000
1!
b0000000100000000 )
b0000000100000000 %
#176000
b1111110100000000 $
b1111110100000000 (
#180000
0!
#190000
1!
b0000000000001100 )
b0000000000001100 %
#196000
b1000000000000000 $
b1000000000000000 (
#200000
0!
#210000
1!
b0000000000000000 )
b0000000000000000 %
