top/mult.v
module mult(
	clk,
	reset,
	in,
	w,
	out
);

//Data is stored as an 8.8 fixed point number
input clk;
input reset;
input [15:0] in;
input [15:0] w;
output [15:0] out;

//Define constants
parameter vecLen=16;

//Define variables
integer i;

reg [31:0] layer1 [15:0];
reg [31:0] layer2 [7:0];
reg [31:0] layer3 [3:0];
reg [31:0] layer4 [1:0];
reg [31:0] layer5;
/***********************************************************************
Because there are 5 layers, this design takes 5 clock cylces to complete
***********************************************************************/


//Tie the output pin to the last register's (layer5) output 
assign out = layer5[23:8];

//Define the pipelined multiplier data path
always @(posedge clk) 
begin
	//If reset is held high, clear the pipelined registers
	if (reset==1) begin
		for (i=0; i<vecLen; i=i+1)begin	
			layer1[i]<=0;
		end	
		for (i=0; i<vecLen/2; i=i+1)begin	
			layer2[i]<=0;
		end
		for (i=0; i<vecLen/4; i=i+1)begin	
			layer3[i]<=0;
		end			
		for (i=0; i<vecLen/8; i=i+1)begin	
			layer4[i]<=0;
		end	
		layer5 <= 0;
		
	end
	//If reset is low, perform normal multiplier operations
	else begin
	/*******************************SIGNED***************************/
		//***************Layer1****************************
		//AND each bit of the weight function with the input	
		layer1[0][16:0]<= {1'b1, ~(w[0] & in[15]), {15{w[0]}} & in[14:0]};
		layer1[1][16:1]<= {~(w[1] & in[15]), {15{w[1]}} & in[14:0]};
		layer1[2][17:2]<= {~(w[2] & in[15]), {15{w[2]}} & in[14:0]};
		layer1[3][18:3]<= {~(w[3] & in[15]), {15{w[3]}} & in[14:0]};
		layer1[4][19:4]<= {~(w[4] & in[15]), {15{w[4]}} & in[14:0]};
		layer1[5][20:5]<= {~(w[5] & in[15]), {15{w[5]}} & in[14:0]};
		layer1[6][21:6]<= {~(w[6] & in[15]), {15{w[6]}} & in[14:0]};
		layer1[7][22:7]<= {~(w[7] & in[15]), {15{w[7]}} & in[14:0]};
		layer1[8][23:8]<= {~(w[8] & in[15]), {15{w[8]}} & in[14:0]};
		layer1[9][24:9]<= {~(w[9] & in[15]), {15{w[9]}} & in[14:0]};
		layer1[10][25:10]<= {~(w[10] & in[15]), {15{w[10]}} & in[14:0]};
		layer1[11][26:11]<= {~(w[11] & in[15]), {15{w[11]}} & in[14:0]};
		layer1[12][27:12]<= {~(w[12] & in[15]), {15{w[12]}} & in[14:0]};
		layer1[13][28:13]<= {~(w[13] & in[15]), {15{w[13]}} & in[14:0]};
		layer1[14][29:14]<= {~(w[14] & in[15]), {15{w[14]}} & in[14:0]};
		layer1[15][31:15]<= {1'b1, (w[15] & in[15]), ~({15{w[15]}} & in[14:0])};

	
		//***************Layer2****************************
		//Start adding the results of the and

		layer2[0] <= layer1[0] + layer1[1];
		layer2[1] <= layer1[2] + layer1[3];
		layer2[2] <= layer1[4] + layer1[5];
		layer2[3] <= layer1[6] + layer1[7];
		layer2[4] <= layer1[8] + layer1[9];
		layer2[5] <= layer1[10] + layer1[11];
		layer2[6] <= layer1[12] + layer1[13];
		layer2[7] <= layer1[14] + layer1[15];
		
		
		//***************Layer3****************************
		//Continue adding outputs
		layer3[0] <= layer2[0] + layer2[1];
		layer3[1] <= layer2[2] + layer2[3];
		layer3[2] <= layer2[4] + layer2[5];
		layer3[3] <= layer2[6] + layer2[7];
		
		//***************Layer4****************************
		//Continue adding outputs
		layer4[0] <= layer3[0] + layer3[1];
		layer4[1] <= layer3[2] + layer3[3];
		
		//***************Layer5****************************
		//Calculate the final result of the multiplier
		layer5 <= layer4[0] + layer4[1];
	/****************************END SIGNED**************************/





	/******************************UNSIGNED***************************
		//***************Layer1****************************
		//AND each bit of the weight function with the input	
		layer1[0][15:0]<= {16{w[0]}} & in;
		layer1[1][16:1]<= {16{w[1]}} & in;
		layer1[2][17:2]<= {16{w[2]}} & in;
		layer1[3][18:3]<= {16{w[3]}} & in;
		layer1[4][19:4]<= {16{w[4]}} & in;
		layer1[5][20:5]<= {16{w[5]}} & in;
		layer1[6][21:6]<= {16{w[6]}} & in;
		layer1[7][22:7]<= {16{w[7]}} & in;
		layer1[8][23:8]<= {16{w[8]}} & in;
		layer1[9][24:9]<= {16{w[9]}} & in;
		layer1[10][25:10]<= {16{w[10]}} & in;
		layer1[11][26:11]<= {16{w[11]}} & in;
		layer1[12][27:12]<= {16{w[12]}} & in;
		layer1[13][28:13]<= {16{w[13]}} & in;
		layer1[14][29:14]<= {16{w[14]}} & in;
		layer1[15][30:15]<= {16{w[15]}} & in;


		//***************Layer2****************************
		//Start adding the results of the and

		layer2[0] <= layer1[0] + layer1[1];
		layer2[1] <= layer1[2] + layer1[3];
		layer2[2] <= layer1[4] + layer1[5];
		layer2[3] <= layer1[6] + layer1[7];
		layer2[4] <= layer1[8] + layer1[9];
		layer2[5] <= layer1[10] + layer1[11];
		layer2[6] <= layer1[12] + layer1[13];
		layer2[7] <= layer1[14] + layer1[15];
		
		
		//***************Layer3****************************
		//Continue adding outputs
		layer3[0] <= layer2[0] + layer2[1];
		layer3[1] <= layer2[2] + layer2[3];
		layer3[2] <= layer2[4] + layer2[5];
		layer3[3] <= layer2[6] + layer2[7];
		
		//***************Layer4****************************
		//Continue adding outputs
		layer4[0] <= layer3[0] + layer3[1];
		layer4[1] <= layer3[2] + layer3[3];
		
		//***************Layer5****************************
		//Calculate the final result of the multiplier
		layer5 <= layer4[0] + layer4[1];
	**************************End Unsigned*****************************/
	end

end


endmodule

top/mac.v
module mac(
	clk,
	reset,
	start,	
	done,	
	mac_in,
	weight,
	mac_out	
);

input clk;
input reset;
input start;	//Set start high whenever you enter a new data set
output done;	//Done is output when the MAC is done and restarting calculations with a new set
input [15:0] mac_in;
input [15:0] weight;
output [15:0] mac_out;

//Define variables
reg [15:0] psum;
wire [15:0] mult_out;

//Stages 1-5 correspond to the multiplier module
//Stage 6 corresponds to the accumulate stage
reg stage1, stage2, stage3, stage4, stage5, stage6;

mult mult1(clk, reset, mac_in, weight, mult_out);



assign mac_out = psum;
assign done = stage6;

always @(posedge clk) 
begin
	//Reset if reset is high 
	if(reset==1) begin
		psum<=0;
		stage1<=0;
		stage2<=0;
		stage3<=0;
		stage4<=0;
		stage5<=0;
	end
	
	//If stage6==1, the next input to psum must be from a new data set
	else if(stage6==1) begin
		#3 psum<=mult_out;

		//Keep track of the delay of data through the pipeline
		stage1<=start;
		stage2<=stage1;
		stage3<=stage2;
		stage4<=stage3;
		stage5<=stage4;
		stage6<=stage5;

	end
	else begin
		//Update the psum
		#3 psum<= psum + mult_out;

		//Keep track of the delay of data through the pipeline
		stage1<=start;
		stage2<=stage1;
		stage3<=stage2;
		stage4<=stage3;
		stage5<=stage4;
		stage6<=stage5;

	end





end

endmodule

top/sram_weight2.v
//SRAMA
module sram_weight2(
clk,
we,
d,
address,
q
);

input clk;	
input we;		//if(we) > [write enable] else > [read enable]
input [15:0] d; 	//data input (high impedance for this design)
input [11:0] address;	//memory address
output reg [15:0] q; 	//output

reg[15:0] mem [0:1999];  

always @(posedge clk)
begin 
	if (we == 1)begin 
	mem[address] <= d; 

	end else if(we == 0)begin 
	q <= mem[address]; 
	end 
end

endmodule

top/sram_weight1.v
//SRAMA
module sram_weight1(
clk,
we,
d,
address,
q
);

input clk;	
input we;		//if(we) > [write enable] else > [read enable]
input [15:0] d; 	//data input (high impedance for this design)
input [17:0] address;	//memory address
output reg [15:0] q; 	//output

reg[15:0] mem [0:156799];  

always @(posedge clk)
begin 
	if (we == 1)begin 
	mem[address] <= d; 

	end else if(we == 0)begin 
	q <= mem[address]; 
	end 
end

endmodule

top/sram_input.v
//SRAMA
module sram_input(
clk,
we,
d,
address,
q
);

input clk;	
input we;		//if(we) > [write enable] else > [read enable]
input signed [15:0] d; 	//data input (high impedance for this design)
input [9:0] address;	//memory address
output reg signed [15:0] q; 	//output

reg signed [15:0] mem [0:783];  

always @(posedge clk)
begin 
	if (we == 1)begin 
	mem[address] <= d; 

	end else if(we == 0)begin 
	q <= mem[address]; 
	end 
end

endmodule

top/top.v
//TOP
module top(
clk,
we_1,
we_2,
we_3,
address_1,
address_2, 
address_3,
mac_start,	
reset
);

//---Inputs---
input clk;
input reset;

//---Wires---

//--write enables and addresses set to INPUT for testing. Change to wires from control
input we_1; // sram_weight1 write enable
input we_2; // sram_weight2 write enable
input we_3; // sram_input write enable


input [17:0] address_1; //sram_weight1 address
input [11:0] address_2; //sram_weight2 address
input [9:0]  address_3; //sram_input address

wire [15:0] d1,d2,d3,d4,d5,d6,d7,d8,d9,d10; //data to sram_input
wire [15:0] in1_0, in2_0, in3_0, in4_0, in5_0, in6_0, in7_0, in8_0, in9_0, in10_0; //output of input SRAM	
wire [15:0] in1_1, in2_1, in3_1, in4_1, in5_1, in6_1, in7_1, in8_1, in9_1, in10_1; //output of 1st MAC
wire [15:0] in1_2, in2_2, in3_2, in4_2, in5_2, in6_2, in7_2, in8_2, in9_2, in10_2; //output of Sigma
wire [15:0] dw1, dw2; //data to sram_weight1(2)
wire [15:0] weight_1, weight_2; //output of sram_weight1(2)
input mac_start; // mac signal set to input for testing
wire  mac_done; // control signal from MAC


//---INPUT SRAM---
sram_input SRAM_INPUT1(.clk(clk),
	.d(d1), 
	.we(we_3),  
	.address(address_3), 
	.q(in1_0)); 
sram_input SRAM_INPUT2(.clk(clk),
	.d(d2), 
	.we(we_3),  
	.address(address_3), 
	.q(in2_0)); 
sram_input SRAM_INPUT3(.clk(clk),
	.d(d3), 
	.we(we_3),  
	.address(address_3), 
	.q(in3_0)); 
sram_input SRAM_INPUT4(.clk(clk),
	.d(d4), 
	.we(we_3),  
	.address(address_3), 
	.q(in4_0)); 
sram_input SRAM_INPUT5(.clk(clk),
	.d(d5), 
	.we(we_3),  
	.address(address_3), 
	.q(in5_0)); 
sram_input SRAM_INPUT6(.clk(clk),
	.d(d6), 
	.we(we_3),  
	.address(address_3), 
	.q(in6_0)); 
sram_input SRAM_INPUT7(.clk(clk),
	.d(d7), 
	.we(we_3),  
	.address(address_3), 
	.q(in7_0)); 
sram_input SRAM_INPUT8(.clk(clk),
	.d(d8), 
	.we(we_3),  
	.address(address_3), 
	.q(in8_0)); 
sram_input SRAM_INPUT9(.clk(clk),
	.d(d9), 
	.we(we_3),  
	.address(address_3), 
	.q(in9_0)); 
sram_input SRAM_INPUT10(.clk(clk),
	.d(d10), 
	.we(we_3),  
	.address(address_3), 
	.q(in10_0)); 

//---WEIGHT SRAMS---
sram_weight1 SRAM_WEIGHT1(.clk(clk),
	.d(dw1), 
	.we(we_1),  
	.address(address_1), 
	.q(weight_1)); 

sram_weight2 SRAM_WEIGHT2(.clk(clk),
	.d(dw2), 
	.we(we_2),  
	.address(address_2), 
	.q(weight_2)); 

//---MAC---
mac MAC1(.clk(clk), 
	.reset(reset),
	.start(mac_start), 
	.done(mac_done),
	.mac_in(in1_0),
	.weight(weight_1),
	.mac_out(in1_1));



/*
control CONTROL(.clk(clk), 
	.reset(reset), 
	.done(done),
	.ps_in(ps_in), 
	.fs_in(fs_in), 
	.address(address),
	.write(write),
	.multiply_enable(multiply_enable),
	.add_enable(add_enable),
	.fs_out(fs_out));

mult MULT(.clk(clk), 
	.product(product),
	.reset(reset),
	.done(done), 
	.multiply_enable(multiply_enable),
	.A(A),  //multiplier from srama
	.B(B));  //multiplier from sramb
	//.PRODUCT(PRODUCT)); //truncated floating point product 
*/

	




endmodule

top/top_tb.v

`timescale 1ns / 1ps

module top_tb();
	reg clk;
	reg we; //testing
	reg [17:0] address_1; //testing
	reg [11:0] address_2; //testing
	reg [9:0] address_3; //testing
	reg reset;
	reg mac_start;

	integer i; 
	integer j; 

	
    top DUT(
        .clk(clk),
	.we_1(we), 
	.we_2(we),
	.we_3(we),//testing
	.address_2(address_2), //testing
	.address_1(address_1),	
	.address_3(address_3),	
	.mac_start(mac_start), 
        .reset(reset)
        );

    initial
    begin
        $dumpfile("top.vcd");
        $dumpvars(0, top_tb);

	$readmemb("test_image1_fix.txt", DUT.SRAM_INPUT1.mem);
	$readmemb("test_image2_fix.txt", DUT.SRAM_INPUT2.mem);
	$readmemb("test_image3_fix.txt", DUT.SRAM_INPUT3.mem);
	$readmemb("test_image4_fix.txt", DUT.SRAM_INPUT4.mem);
	$readmemb("test_image5_fix.txt", DUT.SRAM_INPUT5.mem);
	$readmemb("test_image6_fix.txt", DUT.SRAM_INPUT6.mem);
	$readmemb("test_image7_fix.txt", DUT.SRAM_INPUT7.mem);
	$readmemb("test_image8_fix.txt", DUT.SRAM_INPUT8.mem);
	$readmemb("test_image9_fix.txt", DUT.SRAM_INPUT9.mem);
	$readmemb("test_image10_fix.txt", DUT.SRAM_INPUT10.mem);

	$readmemb("layer1_weight.txt", DUT.SRAM_WEIGHT1.mem);
	$readmemb("layer2_weight.txt", DUT.SRAM_WEIGHT2.mem);


		clk = 0;
		reset = 1;
		we = 0; //testing
		address_3 = 0; 

		#20		
		reset = 0; 
		mac_start = 1; 

		#20 
		mac_start = 0;


		for (j = 0; j < 784; j=j+1)begin 
		#20
		address_3 = j; 
		address_1 = j; 

		end

		#100
		$finish;

        $finish;
    end

    always 
        #10 clk = !clk;

endmodule

top/top.vcd
$date
	Sat Dec  2 16:11:47 2017
$end

$version
	Synopsys VCS version J-2014.12-SP1-1_Full64
$end

$timescale
	1ps
$end

$comment Csum: 1 4c6f318abf693a81 $end


$scope module top_tb $end
$var reg 1 ! clk $end
$var reg 1 " we $end
$var reg 18 # address_1 [17:0] $end
$var reg 12 $ address_2 [11:0] $end
$var reg 10 % address_3 [9:0] $end
$var reg 1 & reset $end
$var reg 1 ' mac_start $end
$var integer 32 ( i $end
$var integer 32 ) j $end

$scope module DUT $end
$var wire 1 ! clk $end
$var wire 1 & reset $end
$var wire 1 " we_1 $end
$var wire 1 * we_2 $end
$var wire 1 * we_3 $end
$var wire 18 # address_1 [17:0] $end
$var wire 12 $ address_2 [11:0] $end
$var wire 10 % address_3 [9:0] $end
$var wire 16 + d1 [15:0] $end
$var wire 16 , d2 [15:0] $end
$var wire 16 - d3 [15:0] $end
$var wire 16 . d4 [15:0] $end
$var wire 16 / d5 [15:0] $end
$var wire 16 0 d6 [15:0] $end
$var wire 16 1 d7 [15:0] $end
$var wire 16 2 d8 [15:0] $end
$var wire 16 3 d9 [15:0] $end
$var wire 16 4 d10 [15:0] $end
$var wire 16 5 in1_0 [15:0] $end
$var wire 16 6 in2_0 [15:0] $end
$var wire 16 7 in3_0 [15:0] $end
$var wire 16 8 in4_0 [15:0] $end
$var wire 16 9 in5_0 [15:0] $end
$var wire 16 : in6_0 [15:0] $end
$var wire 16 ; in7_0 [15:0] $end
$var wire 16 < in8_0 [15:0] $end
$var wire 16 = in9_0 [15:0] $end
$var wire 16 > in10_0 [15:0] $end
$var wire 16 ? in1_1 [15:0] $end
$var wire 16 @ in2_1 [15:0] $end
$var wire 16 A in3_1 [15:0] $end
$var wire 16 B in4_1 [15:0] $end
$var wire 16 C in5_1 [15:0] $end
$var wire 16 D in6_1 [15:0] $end
$var wire 16 E in7_1 [15:0] $end
$var wire 16 F in8_1 [15:0] $end
$var wire 16 G in9_1 [15:0] $end
$var wire 16 H in10_1 [15:0] $end
$var wire 16 I in1_2 [15:0] $end
$var wire 16 J in2_2 [15:0] $end
$var wire 16 K in3_2 [15:0] $end
$var wire 16 L in4_2 [15:0] $end
$var wire 16 M in5_2 [15:0] $end
$var wire 16 N in6_2 [15:0] $end
$var wire 16 O in7_2 [15:0] $end
$var wire 16 P in8_2 [15:0] $end
$var wire 16 Q in9_2 [15:0] $end
$var wire 16 R in10_2 [15:0] $end
$var wire 16 S dw1 [15:0] $end
$var wire 16 T dw2 [15:0] $end
$var wire 1 U weight_1 [15] $end
$var wire 1 V weight_1 [14] $end
$var wire 1 W weight_1 [13] $end
$var wire 1 X weight_1 [12] $end
$var wire 1 Y weight_1 [11] $end
$var wire 1 Z weight_1 [10] $end
$var wire 1 [ weight_1 [9] $end
$var wire 1 \ weight_1 [8] $end
$var wire 1 ] weight_1 [7] $end
$var wire 1 ^ weight_1 [6] $end
$var wire 1 _ weight_1 [5] $end
$var wire 1 ` weight_1 [4] $end
$var wire 1 a weight_1 [3] $end
$var wire 1 b weight_1 [2] $end
$var wire 1 c weight_1 [1] $end
$var wire 1 d weight_1 [0] $end
$var wire 16 e weight_2 [15:0] $end
$var wire 1 ' mac_start $end
$var wire 1 f mac_done $end

$scope module SRAM_INPUT1 $end
$var wire 1 g clk $end
$var wire 1 * we $end
$var wire 16 + d [15:0] $end
$var wire 10 h address [9:0] $end
$var reg 16 i q [15:0] $end
$upscope $end


$scope module SRAM_INPUT2 $end
$var wire 1 g clk $end
$var wire 1 * we $end
$var wire 16 , d [15:0] $end
$var wire 10 h address [9:0] $end
$var reg 16 j q [15:0] $end
$upscope $end


$scope module SRAM_INPUT3 $end
$var wire 1 g clk $end
$var wire 1 * we $end
$var wire 16 - d [15:0] $end
$var wire 10 h address [9:0] $end
$var reg 16 k q [15:0] $end
$upscope $end


$scope module SRAM_INPUT4 $end
$var wire 1 g clk $end
$var wire 1 * we $end
$var wire 16 . d [15:0] $end
$var wire 10 h address [9:0] $end
$var reg 16 l q [15:0] $end
$upscope $end


$scope module SRAM_INPUT5 $end
$var wire 1 g clk $end
$var wire 1 * we $end
$var wire 16 / d [15:0] $end
$var wire 10 h address [9:0] $end
$var reg 16 m q [15:0] $end
$upscope $end


$scope module SRAM_INPUT6 $end
$var wire 1 g clk $end
$var wire 1 * we $end
$var wire 16 0 d [15:0] $end
$var wire 10 h address [9:0] $end
$var reg 16 n q [15:0] $end
$upscope $end


$scope module SRAM_INPUT7 $end
$var wire 1 g clk $end
$var wire 1 * we $end
$var wire 16 1 d [15:0] $end
$var wire 10 h address [9:0] $end
$var reg 16 o q [15:0] $end
$upscope $end


$scope module SRAM_INPUT8 $end
$var wire 1 g clk $end
$var wire 1 * we $end
$var wire 16 2 d [15:0] $end
$var wire 10 h address [9:0] $end
$var reg 16 p q [15:0] $end
$upscope $end


$scope module SRAM_INPUT9 $end
$var wire 1 g clk $end
$var wire 1 * we $end
$var wire 16 3 d [15:0] $end
$var wire 10 h address [9:0] $end
$var reg 16 q q [15:0] $end
$upscope $end


$scope module SRAM_INPUT10 $end
$var wire 1 g clk $end
$var wire 1 * we $end
$var wire 16 4 d [15:0] $end
$var wire 10 h address [9:0] $end
$var reg 16 r q [15:0] $end
$upscope $end


$scope module SRAM_WEIGHT1 $end
$var wire 1 ! clk $end
$var wire 1 " we $end
$var wire 16 S d [15:0] $end
$var wire 18 # address [17:0] $end
$var reg 16 s q [15:0] $end
$upscope $end


$scope module SRAM_WEIGHT2 $end
$var wire 1 ! clk $end
$var wire 1 * we $end
$var wire 16 T d [15:0] $end
$var wire 12 $ address [11:0] $end
$var reg 16 e q [15:0] $end
$upscope $end


$scope module MAC1 $end
$var wire 1 ! clk $end
$var wire 1 & reset $end
$var wire 1 ' start $end
$var wire 1 f done $end
$var wire 16 5 mac_in [15:0] $end
$var wire 1 U weight [15] $end
$var wire 1 V weight [14] $end
$var wire 1 W weight [13] $end
$var wire 1 X weight [12] $end
$var wire 1 Y weight [11] $end
$var wire 1 Z weight [10] $end
$var wire 1 [ weight [9] $end
$var wire 1 \ weight [8] $end
$var wire 1 ] weight [7] $end
$var wire 1 ^ weight [6] $end
$var wire 1 _ weight [5] $end
$var wire 1 ` weight [4] $end
$var wire 1 a weight [3] $end
$var wire 1 b weight [2] $end
$var wire 1 c weight [1] $end
$var wire 1 d weight [0] $end
$var wire 16 ? mac_out [15:0] $end
$var reg 16 t psum [15:0] $end
$var wire 16 u mult_out [15:0] $end
$var reg 1 v stage1 $end
$var reg 1 w stage2 $end
$var reg 1 x stage3 $end
$var reg 1 y stage4 $end
$var reg 1 z stage5 $end
$var reg 1 { stage6 $end

$scope module mult1 $end
$var wire 1 ! clk $end
$var wire 1 & reset $end
$var wire 16 5 in [15:0] $end
$var wire 1 U w [15] $end
$var wire 1 V w [14] $end
$var wire 1 W w [13] $end
$var wire 1 X w [12] $end
$var wire 1 Y w [11] $end
$var wire 1 Z w [10] $end
$var wire 1 [ w [9] $end
$var wire 1 \ w [8] $end
$var wire 1 ] w [7] $end
$var wire 1 ^ w [6] $end
$var wire 1 _ w [5] $end
$var wire 1 ` w [4] $end
$var wire 1 a w [3] $end
$var wire 1 b w [2] $end
$var wire 1 c w [1] $end
$var wire 1 d w [0] $end
$var wire 16 u out [15:0] $end
$var integer 32 | i $end
$var reg 32 } layer5 [31:0] $end
$upscope $end

$upscope $end

$upscope $end

$upscope $end

$enddefinitions $end

#0
$dumpvars
0!
xf
x'
1&
xv
xw
xx
xy
xz
x{
0"
xd
xZ
xY
xX
xW
xV
xU
xc
xb
xa
x`
x_
x^
x]
x\
x[
bxxxxxxxxxxxxxxxxxxxxxxxxxxxxxxxx |
bxxxxxxxxxxxxxxxx e
bxxxxxxxxxxxxxxxxxx #
bxxxxxxxxxxxx $
b0000000000 %
bzzzzzzzzzzzzzzzz S
bzzzzzzzzzzzzzzzz T
bxxxxxxxxxxxxxxxxxxxxxxxxxxxxxxxx (
bxxxxxxxxxxxxxxxx >
bzzzzzzzzzzzzzzzz H
bzzzzzzzzzzzzzzzz R
bxxxxxxxxxxxxxxxx 5
bzzzzzzzzzzzzzzzz I
bxxxxxxxxxxxxxxxx 6
bzzzzzzzzzzzzzzzz @
bzzzzzzzzzzzzzzzz J
bxxxxxxxxxxxxxxxx 7
bzzzzzzzzzzzzzzzz A
bzzzzzzzzzzzzzzzz K
bxxxxxxxxxxxxxxxx 8
bzzzzzzzzzzzzzzzz B
bzzzzzzzzzzzzzzzz L
bxxxxxxxxxxxxxxxx 9
bzzzzzzzzzzzzzzzz C
bzzzzzzzzzzzzzzzz M
bxxxxxxxxxxxxxxxx :
bzzzzzzzzzzzzzzzz D
bzzzzzzzzzzzzzzzz N
bxxxxxxxxxxxxxxxx ;
bzzzzzzzzzzzzzzzz E
bzzzzzzzzzzzzzzzz O
bxxxxxxxxxxxxxxxx <
bzzzzzzzzzzzzzzzz F
bzzzzzzzzzzzzzzzz P
bxxxxxxxxxxxxxxxx =
bzzzzzzzzzzzzzzzz G
bzzzzzzzzzzzzzzzz Q
bxxxxxxxxxxxxxxxxxxxxxxxxxxxxxxxx )
bxxxxxxxxxxxxxxxxxxxxxxxxxxxxxxxx }
bxxxxxxxxxxxxxxxx ?
bxxxxxxxxxxxxxxxx u
bxxxxxxxxxxxxxxxx t
bxxxxxxxxxxxxxxxx s
bxxxxxxxxxxxxxxxx i
bxxxxxxxxxxxxxxxx j
bxxxxxxxxxxxxxxxx k
bxxxxxxxxxxxxxxxx l
bxxxxxxxxxxxxxxxx m
bxxxxxxxxxxxxxxxx n
bxxxxxxxxxxxxxxxx o
bxxxxxxxxxxxxxxxx p
bxxxxxxxxxxxxxxxx q
bxxxxxxxxxxxxxxxx r
bzzzzzzzzzzzzzzzz +
0*
bzzzzzzzzzzzzzzzz ,
bzzzzzzzzzzzzzzzz -
bzzzzzzzzzzzzzzzz .
bzzzzzzzzzzzzzzzz /
bzzzzzzzzzzzzzzzz 0
bzzzzzzzzzzzzzzzz 1
bzzzzzzzzzzzzzzzz 2
bzzzzzzzzzzzzzzzz 3
bzzzzzzzzzzzzzzzz 4
0g
b0000000000 h
$end
#10000
1!
1g
b00000000000000000000000000000010 |
b0000000000000000 t
b0000000000000000 ?
0v
0w
0x
0y
0z
b00000000000000000000000000000000 }
b0000000000000000 u
b0000000000000000 i
b0000000000000000 5
b0000000000000000 j
b0000000000000000 6
b0000000000000000 k
b0000000000000000 7
b0000000000000000 l
b0000000000000000 8
b0000000000000000 m
b0000000000000000 9
b0000000000000000 n
b0000000000000000 :
b0000000000000000 o
b0000000000000000 ;
b0000000000000000 p
b0000000000000000 <
b0000000000000000 q
b0000000000000000 =
b0000000000000000 r
b0000000000000000 >
#20000
0&
1'
0!
0g
#30000
1!
1g
#33000
1v
0{
0f
#40000
0'
b00000000000000000000000000000000 )
0!
0g
#50000
1!
1g
#53000
0v
1w
#60000
b000000000000000000 #
b00000000000000000000000000000001 )
0!
0g
#70000
1!
1g
b0000000001000110 s
0U
0V
0W
0X
0Y
0Z
0[
0\
0]
1^
0_
0`
0a
1b
1c
0d
#73000
0w
1x
#80000
b0000000001 %
b0000000001 h
b000000000000000001 #
b00000000000000000000000000000010 )
0!
0g
#90000
1!
1g
b1111111111110110 s
1U
1V
1W
1X
1Y
1Z
1[
1\
1]
1_
1`
#93000
0x
1y
#100000
b0000000010 %
b0000000010 h
b000000000000000010 #
b00000000000000000000000000000011 )
0!
0g
#110000
1!
1g
b1111111111011110 s
0_
1a
#113000
0y
1z
#120000
b0000000011 %
b0000000011 h
b000000000000000011 #
b00000000000000000000000000000100 )
0!
0g
#130000
1!
1g
b0000000000111111 s
0U
0V
0W
0X
0Y
0Z
0[
0\
0]
0^
1_
1d
#133000
0z
1{
1f
#140000
b0000000100 %
b0000000100 h
b000000000000000100 #
b00000000000000000000000000000101 )
0!
0g
#150000
1!
1g
b1111111111010000 s
1U
1V
1W
1X
1Y
1Z
1[
1\
1]
1^
0_
0a
0b
0c
0d
#153000
0{
0f
#160000
b0000000101 %
b0000000101 h
b000000000000000101 #
b00000000000000000000000000000110 )
0!
0g
#170000
1!
1g
b1111111111001001 s
0`
1a
1d
#180000
b0000000110 %
b0000000110 h
b000000000000000110 #
b00000000000000000000000000000111 )
0!
0g
#190000
1!
1g
b1111111110111100 s
0^
1_
1`
1b
0d
#200000
b0000000111 %
b0000000111 h
b000000000000000111 #
b00000000000000000000000000001000 )
0!
0g
#210000
1!
1g
b0000000001001101 s
0U
0V
0W
0X
0Y
0Z
0[
0\
0]
1^
0_
0`
1d
#220000
b0000001000 %
b0000001000 h
b000000000000001000 #
b00000000000000000000000000001001 )
0!
0g
#230000
1!
1g
b0000000000111100 s
0^
1_
1`
0d
#240000
b0000001001 %
b0000001001 h
b000000000000001001 #
b00000000000000000000000000001010 )
0!
0g
#250000
1!
1g
b0000000000010011 s
0_
0a
0b
1c
1d
#260000
b0000001010 %
b0000001010 h
b000000000000001010 #
b00000000000000000000000000001011 )
0!
0g
#270000
1!
1g
b0000000001001110 s
1^
0`
1a
1b
0d
#280000
b0000001011 %
b0000001011 h
b000000000000001011 #
b00000000000000000000000000001100 )
0!
0g
#290000
1!
1g
b1111111111100001 s
1U
1V
1W
1X
1Y
1Z
1[
1\
1]
1_
0a
0b
0c
1d
#300000
b0000001100 %
b0000001100 h
b000000000000001100 #
b00000000000000000000000000001101 )
0!
0g
#310000
1!
1g
b0000000000001000 s
0U
0V
0W
0X
0Y
0Z
0[
0\
0]
0^
0_
1a
0d
#320000
b0000001101 %
b0000001101 h
b000000000000001101 #
b00000000000000000000000000001110 )
0!
0g
#330000
1!
1g
b1111111111110111 s
1U
1V
1W
1X
1Y
1Z
1[
1\
1]
1^
1_
1`
0a
1b
1c
1d
#340000
b0000001110 %
b0000001110 h
b000000000000001110 #
b00000000000000000000000000001111 )
0!
0g
#350000
1!
1g
b1111111111001001 s
0_
0`
1a
0b
0c
#360000
b0000001111 %
b0000001111 h
b000000000000001111 #
b00000000000000000000000000010000 )
0!
0g
#370000
1!
1g
b1111111110111101 s
0^
1_
1`
1b
#380000
b0000010000 %
b0000010000 h
b000000000000010000 #
b00000000000000000000000000010001 )
0!
0g
#390000
1!
1g
b1111111111011111 s
1^
0_
1c
#400000
b0000010001 %
b0000010001 h
b000000000000010001 #
b00000000000000000000000000010010 )
0!
0g
#410000
1!
1g
b1111111111010000 s
0a
0b
0c
0d
#420000
b0000010010 %
b0000010010 h
b000000000000010010 #
b00000000000000000000000000010011 )
0!
0g
#430000
1!
1g
b0000000000101110 s
0U
0V
0W
0X
0Y
0Z
0[
0\
0]
0^
1_
0`
1a
1b
1c
#440000
b0000010011 %
b0000010011 h
b000000000000010011 #
b00000000000000000000000000010100 )
0!
0g
#450000
1!
1g
b1111111111100001 s
1U
1V
1W
1X
1Y
1Z
1[
1\
1]
1^
0a
0b
0c
1d
#460000
b0000010100 %
b0000010100 h
b000000000000010100 #
b00000000000000000000000000010101 )
0!
0g
#470000
1!
1g
b1111111111111111 s
1`
1a
1b
1c
#480000
b0000010101 %
b0000010101 h
b000000000000010101 #
b00000000000000000000000000010110 )
0!
0g
#490000
1!
1g
b1111111111011100 s
0_
0c
0d
#500000
b0000010110 %
b0000010110 h
b000000000000010110 #
b00000000000000000000000000010111 )
0!
0g
#510000
1!
1g
b0000000000100111 s
0U
0V
0W
0X
0Y
0Z
0[
0\
0]
0^
1_
0`
0a
1c
1d
#520000
b0000010111 %
b0000010111 h
b000000000000010111 #
b00000000000000000000000000011000 )
0!
0g
#530000
1!
1g
b1111111111001000 s
1U
1V
1W
1X
1Y
1Z
1[
1\
1]
1^
0_
1a
0b
0c
0d
#540000
b0000011000 %
b0000011000 h
b000000000000011000 #
b00000000000000000000000000011001 )
0!
0g
#550000
1!
1g
b0000000001001110 s
0U
0V
0W
0X
0Y
0Z
0[
0\
0]
1b
1c
#560000
b0000011001 %
b0000011001 h
b000000000000011001 #
b00000000000000000000000000011010 )
0!
0g
#570000
1!
1g
b0000000000001000 s
0^
0b
0c
#580000
b0000011010 %
b0000011010 h
b000000000000011010 #
b00000000000000000000000000011011 )
0!
0g
#590000
1!
1g
b1111111111101011 s
1U
1V
1W
1X
1Y
1Z
1[
1\
1]
1^
1_
1c
1d
#600000
b0000011011 %
b0000011011 h
b000000000000011011 #
b00000000000000000000000000011100 )
0!
0g
#610000
1!
1g
b1111111111101001 s
0c
#620000
b0000011100 %
b0000011100 h
b000000000000011100 #
b00000000000000000000000000011101 )
0!
0g
#630000
1!
1g
b0000000000110000 s
0U
0V
0W
0X
0Y
0Z
0[
0\
0]
0^
1`
0a
0d
